optim_management/__init__.py
optim_management/analysis.py
optim_management/cmd.py
optim_management/optimizer.py
optim_management-2.6.0.dist-info/LICENSE.txt
optim_management-2.6.0.dist-info/METADATA
optim_management-2.6.0.dist-info/WHEEL
optim_management-2.6.0.dist-info/entry_points.txt
optim_management-2.6.0.dist-info/top_level.txt
optim_management-2.6.0.dist-info/RECORD
