Metadata-Version: 2.2
Name: optim_management
Version: 2.6.0
Summary: A package to optimize agricultural practices from crop model outputs
Author: Argeo ULRICH
Author-email: Cyrille MIDINGOYI <cyrille_ahmed.midingoyi@cirad.fr>
Maintainer-email: Cyrille MIDINGOYI <cyrille_ahmed.midingoyi@cirad.fr>
License: MIT License
Project-URL: Homepage, https://github.com/cropmodelingplatform/Optim_management
Project-URL: documentation, https://Optim_management.readthedocs.io
Project-URL: Repository, https://github.com/CropModelingPlatform/Optim_management.git
Classifier: Development Status :: 3 - Alpha
Classifier: Topic :: Software Development :: Build Tools
Classifier: License :: OSI Approved :: MIT License
Classifier: Programming Language :: Python :: 3.9
Classifier: Programming Language :: Python :: 3.10
Classifier: Programming Language :: Python :: 3.11
Classifier: Programming Language :: Python :: 3.12
Classifier: Programming Language :: Python :: 3 :: Only
Requires-Python: >=3.9
License-File: LICENSE.txt
Requires-Dist: numpy
Requires-Dist: xarray
Requires-Dist: pathlib
Requires-Dist: pandas
Requires-Dist: netCDF4
Requires-Dist: click
